byzh/ai/__init__.py
byzh/ai/Bdata/__init__.py
byzh/ai/Bdata/get_dataloader.py
byzh/ai/Bdata/merge_dataset.py
byzh/ai/Bdata/standard.py
byzh/ai/Bdata/dataset/base.py
byzh/ai/Bdata/dataset/cifar.py
byzh/ai/Bdata/dataset/mnist.py
byzh/ai/Bdemo/__init__.py
byzh/ai/Bdemo/mnist.py
byzh/ai/Bdemo/simple_nlp.py
byzh/ai/Bdemo/test.py
byzh/ai/Bearly_stop/__init__.py
byzh/ai/Bearly_stop/reloadbyloss.py
byzh/ai/Bearly_stop/stopbyacc.py
byzh/ai/Bearly_stop/stopbyaccdelta.py
byzh/ai/Bearly_stop/stopbyloss.py
byzh/ai/Bearly_stop/stopbylossdelta.py
byzh/ai/Bearly_stop/stopbyoverfitting.py
byzh/ai/Blr_schedulers/__init__.py
byzh/ai/Blr_schedulers/decaylr.py
byzh/ai/Blr_schedulers/warmupdecaylr.py
byzh/ai/Blr_schedulers/warmuplr.py
byzh/ai/Bmodel/SimpleCNN.py
byzh/ai/Bmodel/__init__.py
byzh/ai/Bmodel/lenet5.py
byzh/ai/Bmodel/lstm.py
byzh/ai/Bmodel/resnet18.py
byzh/ai/Bmodel/rnn.py
byzh/ai/Bmodel/sresnet18.py
byzh/ai/Bmodel/stcn.py
byzh/ai/Bmodel/tcn.py
byzh/ai/Bmodel/study_rnn/__init__.py
byzh/ai/Bmodel/study_rnn/lstm.py
byzh/ai/Bmodel/study_rnn/rnn.py
byzh/ai/Bmodel/transformers/layers.py
byzh/ai/Bmodel/transformers/transformer.py
byzh/ai/Bmodel/transformers/transformer_cls.py
byzh/ai/Bmodel/transformers/utils.py
byzh/ai/Btrainer/__init__.py
byzh/ai/Btrainer/classification_trainer.py
byzh/ai/Btrainer/ddp_trainer.py
byzh/ai/Btrainer/regression_trainer.py
byzh/ai/Btrainer/trainer.py
byzh/ai/Butils/__init__.py
byzh/ai/Butils/get_device.py
byzh/ai/Butils/get_flops.py
byzh/ai/Butils/get_gpu.py
byzh/ai/Butils/get_params.py
byzh/ai/Butils/grid_func.py
byzh/ai/Butils/load_model.py
byzh/ai/Butils/model_tree.py
byzh/ai/Butils/run_maker.py
byzh/ai/Bvisual/__init__.py
byzh/ai/Bvisual/draw_confusion_matrix.py
byzh/ai/Bvisual/draw_loss_acc.py
byzh_ai-0.0.9.46.dist-info/LICENSE
byzh_ai-0.0.9.46.dist-info/METADATA
byzh_ai-0.0.9.46.dist-info/WHEEL
byzh_ai-0.0.9.46.dist-info/top_level.txt
byzh_ai-0.0.9.46.dist-info/RECORD
