Metadata-Version: 2.1
Name: byzh-ai
Version: 0.0.9.46
Summary: 更方便的深度学习
Author: byzh_rc
License: MIT
License-File: LICENSE
Requires-Dist: byzh-core>=0.0.9.0
